server.py
chihf_mcp_server-0.1.0.dist-info/METADATA
chihf_mcp_server-0.1.0.dist-info/WHEEL
chihf_mcp_server-0.1.0.dist-info/entry_points.txt
chihf_mcp_server-0.1.0.dist-info/top_level.txt
chihf_mcp_server-0.1.0.dist-info/RECORD
