Metadata-Version: 2.4
Name: chihf-mcp-server
Version: 0.1.0
Summary: A simple MCP server for Android devices
Requires-Python: >=3.12
Requires-Dist: mcp>=1.6.0
Requires-Dist: openai>=1.75.0
Requires-Dist: requests>=2.32.3
Requires-Dist: uiautomator2>=3.2.9
